{
  "date": "2026-07-16",
  "image": "2026-07-16.png",
  "caption": "The direct-to-video era never died — it just got a compute budget.\n\nAI studios are running the classic B-movie playbook: ride the blockbuster wave, cut the costs, ship fast. Old Hollywood hustle, new Hollywood tools.\n\nThe economics make sense. The content... we'll see. 🎬\n\n#AIFilm #GenerativeAI #AIVideo #DirectToVideo #AICreators #CreatorEconomy",
  "story": {
    "title": "AI startups release direct-to-video generated films as cash-grab strategy",
    "dek": "An AI startup is capitalizing on blockbuster hype by rushing out AI-generated films directly to digital release, mirroring decades-old direct-to-video B-movie economics.",
    "src": "The Verge AI",
    "url": "https://www.theverge.com/entertainment/965616/ash-koosha-odysseus-the-fall-foundtain-zero-tilly-norwood"
  }
}
